cvannotate/__init__.py
cvannotate/cli.py
cvannotate/convert.py
cvannotate/types.py
cvannotate/converters/__init__.py
cvannotate/converters/coco.py
cvannotate/converters/voc.py
cvannotate/converters/yolo.py
cvannotate-1.0.0.dist-info/licenses/LICENSE
cvannotate-1.0.0.dist-info/METADATA
cvannotate-1.0.0.dist-info/WHEEL
cvannotate-1.0.0.dist-info/entry_points.txt
cvannotate-1.0.0.dist-info/top_level.txt
cvannotate-1.0.0.dist-info/RECORD
