Metadata-Version: 2.4
Name: cvannotate
Version: 1.0.0
Summary: Convert object detection annotations across formats (YOLO, VOC, COCO)
Author-email: Guillermo Alcantara <guillermo.alcantara@example.com>
License: MIT
Project-URL: Homepage, https://github.com/Echo9k/cv-format-annotation-converters
Project-URL: Documentation, https://github.com/Echo9k/cv-format-annotation-converters#readme
Project-URL: Repository, https://github.com/Echo9k/cv-format-annotation-converters
Project-URL: Issues, https://github.com/Echo9k/cv-format-annotation-converters/issues
Keywords: computer-vision,annotations,object-detection,yolo,voc,coco
Classifier: Development Status :: 5 - Production/Stable
Classifier: Intended Audience :: Developers
Classifier: Intended Audience :: Science/Research
Classifier: Programming Language :: Python :: 3
Classifier: Programming Language :: Python :: 3.8
Classifier: Programming Language :: Python :: 3.9
Classifier: Programming Language :: Python :: 3.10
Classifier: Programming Language :: Python :: 3.11
Classifier: Programming Language :: Python :: 3.12
Classifier: Topic :: Scientific/Engineering :: Artificial Intelligence
Classifier: Topic :: Software Development :: Libraries :: Python Modules
Requires-Python: >=3.8
License-File: LICENSE
Requires-Dist: typer>=0.9.0
Requires-Dist: pillow>=8.0.0
Requires-Dist: defusedxml>=0.7.0
Provides-Extra: dev
Requires-Dist: pytest>=6.0; extra == "dev"
Requires-Dist: pytest-cov; extra == "dev"
Requires-Dist: black; extra == "dev"
Requires-Dist: isort; extra == "dev"
Requires-Dist: flake8; extra == "dev"
Requires-Dist: mypy; extra == "dev"
Dynamic: license-file
